{
    "_id": {
        "$oid": "571ddebe6e610fc80c4198d1"
    },
    "first-words": [
        "Narwhal",
        "selvage",
        "mollit",
        "chartreuse",
        "freegan",
        "PBR&B",
        "health",
        "goth",
        "cillum",
        "Helvetica",
        "culpa",
        "eiusmod",
        "lo-fi",
        "taxidermy",
        "franzen",
        "velit",
        "chillwave",
        "meditation",
        "quinoa",
        "deep",
        "sriracha",
        "etsy",
        "irure",
        "fugiat",
        "Vice",
        "butcher",
        "nostrud",
        "cray",
        "food",
        "truck",
        "letterpress",
        "pour-over",
        "next",
        "level",
        "readymade",
        "odio",
        "pabst",
        "aesthetic",
        "Single-origin",
        "coffee",
        "hashtag",
        "vero",
        "venmo",
        "semiotics",
        "small",
        "batch",
        "chambray",
        "fingerstache",
        "disrupt",
        "kickstarter",
        "denim",
        "huge",
        "flannel",
        "master",
        "cleanse",
        "flexitarian",
        "lomo",
        "Polaroid",
        "fixie",
        "sustainable",
        "cred",
        "Reprehenderit",
        "offal",
        "tote",
        "aliquip",
        "vinyl",
        "actually",
        "knausgaard",
        "tofu",
        "meggings",
        "Stumptown",
        "leggings",
        "gluten-free",
        "Selfies",
        "viral",
        "pitchfork",
        "biodiesel",
        "sartorial",
        "microdosing",
        "Asymmetrical",
        "nisi",
        "paleo",
        "wayfarers",
        "tilde",
        "pariatur",
        "accusamus",
        "pug",
        "waistcoat",
        "mixtape",
        "listicle",
        "aliqua",
        "kale",
        "chips",
        "portland",
        "DIY",
        "dreamcatcher",
        "fanny",
        "pack",
        "mumblecore",
        "Poutine",
        "plaid",
        "probably",
        "haven't",
        "heard",
        "them",
        "deserunt",
        "literally",
        "Delectus",
        "shoreditch",
        "Gentrify",
        "scenester",
        "street",
        "trust",
        "fund",
        "iPhone",
        "Banh",
        "drinking",
        "vinegar",
        "hella",
        "jean",
        "shorts",
        "jorts",
        "Mlkshk",
        "neutra",
        "henley",
        "whatever",
        "pop-up",
        "brunch",
        "aute",
        "migas",
        "tacos",
        "Gastropub",
        "beer",
        "ipa",
        "intelligentsia",
        "Typewriter",
        "consectetur",
        "adipisicing",
        "blue",
        "label",
        "bottle",
        "photo",
        "booth",
        "sint",
        "thundercats",
        "Irony",
        "pickled",
        "cardigan",
        "twee",
        "ethical",
        "austin",
        "bicycle",
        "bike",
        "six",
        "gear",
        "shift",
        "kinfolk",
        "cornhole",
        "brooklyn",
        "dolore"
    ],
    "second-words": [
        "Co.",
        "Inc.",
        "ster",
        "Biz",
        "Code",
        "Tech",
        "Shell",
        "Binary",
        "Root",
        "Text",
        "Dev",
        "Agency",
        "Architect",
        "Cloud",
        "Camp",
        "Node",
        "Wire"
    ],
    "buzzwords": {
        "tech": [
            "4G",
            "Agile",
            "Benchmarking",
            "Back-end",
            "Big data",
            "the Bleeding edge",
            "Blog",
            "Bringing your own Device",
            "Bricks-and-clicks",
            "Clickthrough",
            "the Cloud",
            "CloudOps",
            "Collaboration",
            "Content management",
            "Content Management Systems",
            "Convergence",
            "Cross-platform",
            "Cyber-physical Systems",
            "Datafication",
            "Data mining",
            "Data science",
            "the Deep web",
            "Design pattern",
            "DevOps",
            "the Digital Divide",
            "Digital Remastering",
            "Digital Rights Management",
            "Digital signage",
            "Disruptive Technologies",
            "Document management",
            "Dot-bomb",
            "E-learning",
            "Enterprise Content Management",
            "Evolution",
            "Framework",
            "Folksonomy",
            "Fuzzy logic",
            "Growth Hacking",
            "Immersion",
            "Information superhighway",
            "Internet of Things",
            "Innovation",
            "Mashu",
            "Mobile",
            "Modularity",
            "Nanotechnology",
            "Netiquette",
            "Network Function virtualization",
            "Next Generation",
            "Object-Oriented Programming",
            "Omnichannel",
            "Pandering",
            "Parsing",
            "PaaS",
            "Podcasting",
            "Portal",
            "Real-time",
            "Responsive Web Design",
            "Sensorization",
            "SaaS",
            "Scalability",
            "Skeuomorphic",
            "Social bookmarking",
            "Social software",
            "Software defined Networking",
            "Spam",
            "Struts",
            "Sync-up",
            "Systems Development Life-Cycle",
            "Tagging",
            "this Thinking outside the box",
            "Thought Leader",
            "Transmedia",
            "User generated content",
            "Viral",
            "Virtualization",
            "Vlogging",
            "Vortal",
            "Web 2.0",
            "Webinars",
            "Weblog",
            "Web services",
            "Wikiality",
            "Workflow"
        ],
        "business": [
            "Analytics",
            "Ballpark figure",
            "Bandwidth",
            "Business-to-Business",
            "Business-to-Consumer",
            "Best of Breed",
            "Best practices",
            "Business Method",
            "Brand",
            "Brick-and-mortar",
            "Business process outsourcing",
            "Buzzword compliant",
            "Building Capabilities",
            "Circle Back",
            "Client-centric",
            "Cloud computing",
            "Close the loop",
            "Co-opetition",
            "Come-to-Jesus moment",
            "Content marketing",
            "Core competency",
            "Creative",
            "Customer-centric",
            "Deep dive",
            "Downsizing",
            "Drill down",
            "Early-stage",
            "Employer Branding",
            "Enablement",
            "Entitlement",
            "Enterprise",
            "Event horizon",
            "Fulfilment issues",
            "Generation Y",
            "Granular",
            "Herding cats",
            "holistic approach",
            "Holistic integration",
            "Hyperlocal",
            "Innovation",
            "Innovation",
            "Knowledge Process Outsourcing",
            "Leverage",
            "Logistics",
            "Long Tail",
            "Low Hanging Fruit",
            "Make it pop",
            "Mindshare",
            "Mission Critical",
            "Management Visibility",
            "New economy",
            "Next generation",
            "Offshoring",
            "Pain point",
            "Paralysis by Analysis",
            "Part of our DNA",
            "Peel back the onion",
            "Pick and Shovel Work",
            "Profit center",
            "Quick-win",
            "Return on Investment",
            "Reverse fulfilment",
            "Rightshoring",
            "Seamless integration",
            "Serum",
            "Share options",
            "Short Runway",
            "Silo",
            "Social Currency",
            "Socialize",
            "Solution",
            "SOX",
            "Sustainability",
            "Storytelling",
            "Startup",
            "Strategy",
            "Synergy",
            "Take Offline",
            "Talent Relationship Management",
            "Tee off",
            "Touch Base",
            "Touchpoint",
            "Upselling",
            "Upcycling",
            "Value-added",
            "Visibility"
        ]
    }
}
